SUSTech/__init__.py
SUSTech-2019.10.19.dist-info/LICENSE
SUSTech-2019.10.19.dist-info/METADATA
SUSTech-2019.10.19.dist-info/WHEEL
SUSTech-2019.10.19.dist-info/top_level.txt
SUSTech-2019.10.19.dist-info/RECORD
